{
  "Timestamp": "2025-11-21 12:11:21",
  "AnalysisMethod": "eDiscovery Compliance Search",
  "InputFile": "Items_0_2025-11-20_22-09-09.csv",
  "TotalFilesScanned": 4423,
  "FilesWithDetections": 4423,
  "TotalSITInstances": 37555,
  "TotalDetectionRows": 10308,
  "SitesWithDetections": 4,
  "UniqueSITTypes": 7,
  "AvgSITsPerFile": 2.33,
  "TopSITTypes": [
    {
      "SIT_Type": "U.S. Social Security Number (SSN)",
      "Files": 2255,
      "Total_Instances": 2255.0
    },
    {
      "SIT_Type": "U.S. / U.K. Passport Number",
      "Files": 2070,
      "Total_Instances": 2070.0
    },
    {
      "SIT_Type": "U.S. Individual Taxpayer Identification Number (ITIN)",
      "Files": 2013,
      "Total_Instances": 2013.0
    }
  ],
  "DetailedCSVPath": "C:\\REPO\\GitHub\\Projects\\Microsoft\\Purview\\Purview-Data-Governance-Simulation\\05-Data-Discovery-Paths\\05b-eDiscovery-Compliance-Search\\scripts\\..\\reports\\eDiscovery-Detailed-Analysis-2025-11-21-121118.csv"
}
